{"day":"2023-05-10","count":165,"from":"2023-05-10T10:26:49.000Z","to":"2023-05-10T20:55:39.000Z","alerts":[{"serialNumber":286,"code":0,"cities":["מטווח ניר עם","ניר עם","שדרות, איבים"],"timestampSec":1683714409,"timestampMs":1683714409000,"timestampIso":"2023-05-10T10:26:49.000Z"},{"serialNumber":287,"code":0,"cities":["בית שקמה","גיאה","כוכב מיכאל","תלמי יפה"],"timestampSec":1683714602,"timestampMs":1683714602000,"timestampIso":"2023-05-10T10:30:02.000Z"},{"serialNumber":287,"code":0,"cities":["ברכיה","הודיה","ניר ישראל"],"timestampSec":1683714606,"timestampMs":1683714606000,"timestampIso":"2023-05-10T10:30:06.000Z"},{"serialNumber":287,"code":0,"cities":["אזור תעשייה צפוני אשקלון","אשקלון - דרום","בת הדר","כפר סילבר","משען"],"timestampSec":1683714614,"timestampMs":1683714614000,"timestampIso":"2023-05-10T10:30:14.000Z"},{"serialNumber":288,"code":0,"cities":["ניר עם","שדרות, איבים"],"timestampSec":1683714898,"timestampMs":1683714898000,"timestampIso":"2023-05-10T10:34:58.000Z"},{"serialNumber":288,"code":0,"cities":["מטווח ניר עם","מפלסים"],"timestampSec":1683714902,"timestampMs":1683714902000,"timestampIso":"2023-05-10T10:35:02.000Z"},{"serialNumber":288,"code":0,"cities":["גבים, מכללת ספיר"],"timestampSec":1683714913,"timestampMs":1683714913000,"timestampIso":"2023-05-10T10:35:13.000Z"},{"serialNumber":289,"code":0,"cities":["מפלסים"],"timestampSec":1683715953,"timestampMs":1683715953000,"timestampIso":"2023-05-10T10:52:33.000Z"},{"serialNumber":290,"code":0,"cities":["מטווח ניר עם","מפלסים"],"timestampSec":1683716233,"timestampMs":1683716233000,"timestampIso":"2023-05-10T10:57:13.000Z"},{"serialNumber":290,"code":0,"cities":["גבים, מכללת ספיר","ניר עם","שדרות, איבים"],"timestampSec":1683716236,"timestampMs":1683716236000,"timestampIso":"2023-05-10T10:57:16.000Z"},{"serialNumber":290,"code":0,"cities":["נתיב העשרה"],"timestampSec":1683716273,"timestampMs":1683716273000,"timestampIso":"2023-05-10T10:57:53.000Z"},{"serialNumber":290,"code":0,"cities":["ארז","אזור תעשייה הדרומי אשקלון"],"timestampSec":1683716278,"timestampMs":1683716278000,"timestampIso":"2023-05-10T10:57:58.000Z"},{"serialNumber":290,"code":0,"cities":["זיקים"],"timestampSec":1683716284,"timestampMs":1683716284000,"timestampIso":"2023-05-10T10:58:04.000Z"},{"serialNumber":290,"code":0,"cities":["יד מרדכי"],"timestampSec":1683716297,"timestampMs":1683716297000,"timestampIso":"2023-05-10T10:58:17.000Z"},{"serialNumber":290,"code":0,"cities":["אשקלון - דרום"],"timestampSec":1683716335,"timestampMs":1683716335000,"timestampIso":"2023-05-10T10:58:55.000Z"},{"serialNumber":290,"code":0,"cities":["ניר עם","שדרות, איבים"],"timestampSec":1683716336,"timestampMs":1683716336000,"timestampIso":"2023-05-10T10:58:56.000Z"},{"serialNumber":290,"code":0,"cities":["מפלסים","מטווח ניר עם"],"timestampSec":1683716339,"timestampMs":1683716339000,"timestampIso":"2023-05-10T10:58:59.000Z"},{"serialNumber":290,"code":0,"cities":["אשקלון - צפון"],"timestampSec":1683716347,"timestampMs":1683716347000,"timestampIso":"2023-05-10T10:59:07.000Z"},{"serialNumber":290,"code":0,"cities":["כרמיה"],"timestampSec":1683716350,"timestampMs":1683716350000,"timestampIso":"2023-05-10T10:59:10.000Z"},{"serialNumber":290,"code":0,"cities":["ארז","נתיב העשרה"],"timestampSec":1683716351,"timestampMs":1683716351000,"timestampIso":"2023-05-10T10:59:11.000Z"},{"serialNumber":290,"code":0,"cities":["גבים, מכללת ספיר"],"timestampSec":1683716358,"timestampMs":1683716358000,"timestampIso":"2023-05-10T10:59:18.000Z"},{"serialNumber":290,"code":0,"cities":["אזור תעשייה הדרומי אשקלון"],"timestampSec":1683716423,"timestampMs":1683716423000,"timestampIso":"2023-05-10T11:00:23.000Z"},{"serialNumber":290,"code":0,"cities":["אשקלון - דרום"],"timestampSec":1683716424,"timestampMs":1683716424000,"timestampIso":"2023-05-10T11:00:24.000Z"},{"serialNumber":290,"code":0,"cities":["זיקים"],"timestampSec":1683716437,"timestampMs":1683716437000,"timestampIso":"2023-05-10T11:00:37.000Z"},{"serialNumber":290,"code":0,"cities":["כרמיה"],"timestampSec":1683716438,"timestampMs":1683716438000,"timestampIso":"2023-05-10T11:00:38.000Z"},{"serialNumber":290,"code":0,"cities":["ניר עם","שדרות, איבים"],"timestampSec":1683716471,"timestampMs":1683716471000,"timestampIso":"2023-05-10T11:01:11.000Z"},{"serialNumber":290,"code":0,"cities":["גבים, מכללת ספיר"],"timestampSec":1683716472,"timestampMs":1683716472000,"timestampIso":"2023-05-10T11:01:12.000Z"},{"serialNumber":290,"code":0,"cities":["נחל עוז"],"timestampSec":1683716475,"timestampMs":1683716475000,"timestampIso":"2023-05-10T11:01:15.000Z"},{"serialNumber":290,"code":0,"cities":["מטווח ניר עם"],"timestampSec":1683716478,"timestampMs":1683716478000,"timestampIso":"2023-05-10T11:01:18.000Z"},{"serialNumber":290,"code":0,"cities":["כפר אביב","כרם ביבנה","שדמה"],"timestampSec":1683716483,"timestampMs":1683716483000,"timestampIso":"2023-05-10T11:01:23.000Z"},{"serialNumber":290,"code":0,"cities":["אשקלון - דרום","אזור תעשייה הדרומי אשקלון"],"timestampSec":1683716484,"timestampMs":1683716484000,"timestampIso":"2023-05-10T11:01:24.000Z"},{"serialNumber":290,"code":0,"cities":["חולית","יתד"],"timestampSec":1683716490,"timestampMs":1683716490000,"timestampIso":"2023-05-10T11:01:30.000Z"},{"serialNumber":290,"code":0,"cities":["זיקים","כרמיה"],"timestampSec":1683716504,"timestampMs":1683716504000,"timestampIso":"2023-05-10T11:01:44.000Z"},{"serialNumber":290,"code":0,"cities":["מבקיעים"],"timestampSec":1683716517,"timestampMs":1683716517000,"timestampIso":"2023-05-10T11:01:57.000Z"},{"serialNumber":290,"code":0,"cities":["ביצרון","בני דרום","גבעת וושינגטון","גן הדרום","גן יבנה","מתחם בני דרום","ניר גלים","קבוצת יבנה"],"timestampSec":1683716520,"timestampMs":1683716520000,"timestampIso":"2023-05-10T11:02:00.000Z"},{"serialNumber":290,"code":0,"cities":["פלמחים"],"timestampSec":1683716543,"timestampMs":1683716543000,"timestampIso":"2023-05-10T11:02:23.000Z"},{"serialNumber":290,"code":0,"cities":["כיסופים","ניצן","אשדוד - ח,ט,י,יג,יד,טז","אשדוד -יא,יב,טו,יז,מרינה,סיט","אשדוד - א,ב,ד,ה","אשדוד - ג,ו,ז"],"timestampSec":1683716545,"timestampMs":1683716545000,"timestampIso":"2023-05-10T11:02:25.000Z"},{"serialNumber":290,"code":0,"cities":["אזור תעשייה צפוני אשקלון","אשקלון - דרום","אשקלון - צפון","באר גנים"],"timestampSec":1683716548,"timestampMs":1683716548000,"timestampIso":"2023-05-10T11:02:28.000Z"},{"serialNumber":290,"code":0,"cities":["שרשרת","מעגלים, גבעולים, מלילות","שיבולים"],"timestampSec":1683716550,"timestampMs":1683716550000,"timestampIso":"2023-05-10T11:02:30.000Z"},{"serialNumber":290,"code":0,"cities":["נתיבות"],"timestampSec":1683716566,"timestampMs":1683716566000,"timestampIso":"2023-05-10T11:02:46.000Z"},{"serialNumber":290,"code":0,"cities":["אזור תעשייה עד הלום","בית עזרא"],"timestampSec":1683716569,"timestampMs":1683716569000,"timestampIso":"2023-05-10T11:02:49.000Z"},{"serialNumber":290,"code":0,"cities":["גן שורק"],"timestampSec":1683716574,"timestampMs":1683716574000,"timestampIso":"2023-05-10T11:02:54.000Z"},{"serialNumber":290,"code":0,"cities":["אשדוד - איזור תעשייה צפוני"],"timestampSec":1683716594,"timestampMs":1683716594000,"timestampIso":"2023-05-10T11:03:14.000Z"},{"serialNumber":290,"code":0,"cities":["נתיב העשרה"],"timestampSec":1683716618,"timestampMs":1683716618000,"timestampIso":"2023-05-10T11:03:38.000Z"},{"serialNumber":290,"code":0,"cities":["אזור תעשייה הדרומי אשקלון"],"timestampSec":1683716625,"timestampMs":1683716625000,"timestampIso":"2023-05-10T11:03:45.000Z"},{"serialNumber":290,"code":0,"cities":["אזור תעשייה צפוני אשקלון","אשקלון - דרום"],"timestampSec":1683716626,"timestampMs":1683716626000,"timestampIso":"2023-05-10T11:03:46.000Z"},{"serialNumber":290,"code":0,"cities":["אשקלון - צפון"],"timestampSec":1683716630,"timestampMs":1683716630000,"timestampIso":"2023-05-10T11:03:50.000Z"},{"serialNumber":291,"code":0,"cities":["כיסופים"],"timestampSec":1683716759,"timestampMs":1683716759000,"timestampIso":"2023-05-10T11:05:59.000Z"},{"serialNumber":292,"code":0,"cities":["אשקלון - דרום"],"timestampSec":1683716870,"timestampMs":1683716870000,"timestampIso":"2023-05-10T11:07:50.000Z"},{"serialNumber":292,"code":0,"cities":["אזור תעשייה הדרומי אשקלון","זיקים","כרמיה"],"timestampSec":1683716875,"timestampMs":1683716875000,"timestampIso":"2023-05-10T11:07:55.000Z"},{"serialNumber":293,"code":0,"cities":["ניר עם","שדרות, איבים"],"timestampSec":1683717055,"timestampMs":1683717055000,"timestampIso":"2023-05-10T11:10:55.000Z"},{"serialNumber":293,"code":0,"cities":["מטווח ניר עם","מפלסים"],"timestampSec":1683717058,"timestampMs":1683717058000,"timestampIso":"2023-05-10T11:10:58.000Z"},{"serialNumber":293,"code":0,"cities":["גבים, מכללת ספיר"],"timestampSec":1683717059,"timestampMs":1683717059000,"timestampIso":"2023-05-10T11:10:59.000Z"},{"serialNumber":293,"code":0,"cities":["נירים"],"timestampSec":1683717119,"timestampMs":1683717119000,"timestampIso":"2023-05-10T11:11:59.000Z"},{"serialNumber":294,"code":0,"cities":["אזור תעשייה הדרומי אשקלון"],"timestampSec":1683717210,"timestampMs":1683717210000,"timestampIso":"2023-05-10T11:13:30.000Z"},{"serialNumber":294,"code":0,"cities":["זיקים"],"timestampSec":1683717223,"timestampMs":1683717223000,"timestampIso":"2023-05-10T11:13:43.000Z"},{"serialNumber":294,"code":0,"cities":["כרמיה"],"timestampSec":1683717226,"timestampMs":1683717226000,"timestampIso":"2023-05-10T11:13:46.000Z"},{"serialNumber":294,"code":0,"cities":["ניר עם","שדרות, איבים"],"timestampSec":1683717289,"timestampMs":1683717289000,"timestampIso":"2023-05-10T11:14:49.000Z"},{"serialNumber":295,"code":0,"cities":["אזור","גבעתיים","רמת גן - מערב","תל אביב - מזרח"],"timestampSec":1683717481,"timestampMs":1683717481000,"timestampIso":"2023-05-10T11:18:01.000Z"},{"serialNumber":295,"code":0,"cities":["נחל עוז"],"timestampSec":1683717545,"timestampMs":1683717545000,"timestampIso":"2023-05-10T11:19:05.000Z"},{"serialNumber":295,"code":0,"cities":["ניר עם","שדרות, איבים"],"timestampSec":1683717551,"timestampMs":1683717551000,"timestampIso":"2023-05-10T11:19:11.000Z"},{"serialNumber":295,"code":0,"cities":["סעד"],"timestampSec":1683717554,"timestampMs":1683717554000,"timestampIso":"2023-05-10T11:19:14.000Z"},{"serialNumber":295,"code":0,"cities":["כפר עזה"],"timestampSec":1683717556,"timestampMs":1683717556000,"timestampIso":"2023-05-10T11:19:16.000Z"},{"serialNumber":295,"code":0,"cities":["זמרת, שובה"],"timestampSec":1683717557,"timestampMs":1683717557000,"timestampIso":"2023-05-10T11:19:17.000Z"},{"serialNumber":295,"code":0,"cities":["תל אביב - דרום העיר ויפו","בת ים","חולון","מקווה ישראל","משמר השבעה"],"timestampSec":1683717560,"timestampMs":1683717560000,"timestampIso":"2023-05-10T11:19:20.000Z"},{"serialNumber":295,"code":0,"cities":["זיקים"],"timestampSec":1683717578,"timestampMs":1683717578000,"timestampIso":"2023-05-10T11:19:38.000Z"},{"serialNumber":295,"code":0,"cities":["אזור תעשייה הדרומי אשקלון"],"timestampSec":1683717582,"timestampMs":1683717582000,"timestampIso":"2023-05-10T11:19:42.000Z"},{"serialNumber":295,"code":0,"cities":["אשקלון - דרום"],"timestampSec":1683717633,"timestampMs":1683717633000,"timestampIso":"2023-05-10T11:20:33.000Z"},{"serialNumber":295,"code":0,"cities":["זיקים"],"timestampSec":1683717640,"timestampMs":1683717640000,"timestampIso":"2023-05-10T11:20:40.000Z"},{"serialNumber":296,"code":0,"cities":["מטווח ניר עם","ניר עם","שדרות, איבים"],"timestampSec":1683717810,"timestampMs":1683717810000,"timestampIso":"2023-05-10T11:23:30.000Z"},{"serialNumber":296,"code":0,"cities":["מפלסים"],"timestampSec":1683717820,"timestampMs":1683717820000,"timestampIso":"2023-05-10T11:23:40.000Z"},{"serialNumber":296,"code":0,"cities":["נחל עוז"],"timestampSec":1683717884,"timestampMs":1683717884000,"timestampIso":"2023-05-10T11:24:44.000Z"},{"serialNumber":297,"code":0,"cities":["פארק תעשיות פלמחים","ראשון לציון - מזרח","בית חנן","בית עובד","גן שורק","נטעים"],"timestampSec":1683718097,"timestampMs":1683718097000,"timestampIso":"2023-05-10T11:28:17.000Z"},{"serialNumber":297,"code":0,"cities":["פלמחים"],"timestampSec":1683718133,"timestampMs":1683718133000,"timestampIso":"2023-05-10T11:28:53.000Z"},{"serialNumber":297,"code":0,"cities":["יבנה"],"timestampSec":1683718142,"timestampMs":1683718142000,"timestampIso":"2023-05-10T11:29:02.000Z"},{"serialNumber":297,"code":0,"cities":["כפר עזה"],"timestampSec":1683718176,"timestampMs":1683718176000,"timestampIso":"2023-05-10T11:29:36.000Z"},{"serialNumber":297,"code":0,"cities":["אזור תעשייה הדרומי אשקלון"],"timestampSec":1683718254,"timestampMs":1683718254000,"timestampIso":"2023-05-10T11:30:54.000Z"},{"serialNumber":297,"code":0,"cities":["זיקים"],"timestampSec":1683718268,"timestampMs":1683718268000,"timestampIso":"2023-05-10T11:31:08.000Z"},{"serialNumber":297,"code":0,"cities":["ניר עם","שדרות, איבים"],"timestampSec":1683718291,"timestampMs":1683718291000,"timestampIso":"2023-05-10T11:31:31.000Z"},{"serialNumber":297,"code":0,"cities":["אזור תעשייה הדרומי אשקלון"],"timestampSec":1683718318,"timestampMs":1683718318000,"timestampIso":"2023-05-10T11:31:58.000Z"},{"serialNumber":297,"code":0,"cities":["זיקים"],"timestampSec":1683718330,"timestampMs":1683718330000,"timestampIso":"2023-05-10T11:32:10.000Z"},{"serialNumber":297,"code":0,"cities":["נירים"],"timestampSec":1683718372,"timestampMs":1683718372000,"timestampIso":"2023-05-10T11:32:52.000Z"},{"serialNumber":297,"code":0,"cities":["נחל עוז"],"timestampSec":1683718411,"timestampMs":1683718411000,"timestampIso":"2023-05-10T11:33:31.000Z"},{"serialNumber":298,"code":0,"cities":["נירים","עין השלושה"],"timestampSec":1683718957,"timestampMs":1683718957000,"timestampIso":"2023-05-10T11:42:37.000Z"},{"serialNumber":299,"code":0,"cities":["נירים"],"timestampSec":1683719259,"timestampMs":1683719259000,"timestampIso":"2023-05-10T11:47:39.000Z"},{"serialNumber":299,"code":0,"cities":["חולית"],"timestampSec":1683719279,"timestampMs":1683719279000,"timestampIso":"2023-05-10T11:47:59.000Z"},{"serialNumber":300,"code":0,"cities":["נירים","עין השלושה"],"timestampSec":1683719380,"timestampMs":1683719380000,"timestampIso":"2023-05-10T11:49:40.000Z"},{"serialNumber":301,"code":0,"cities":["כיסופים"],"timestampSec":1683719733,"timestampMs":1683719733000,"timestampIso":"2023-05-10T11:55:33.000Z"},{"serialNumber":302,"code":0,"cities":["זיקים","נתיב העשרה"],"timestampSec":1683719825,"timestampMs":1683719825000,"timestampIso":"2023-05-10T11:57:05.000Z"},{"serialNumber":302,"code":0,"cities":["פלמחים"],"timestampSec":1683719831,"timestampMs":1683719831000,"timestampIso":"2023-05-10T11:57:11.000Z"},{"serialNumber":302,"code":0,"cities":["חולון","ראשון לציון - מערב"],"timestampSec":1683719836,"timestampMs":1683719836000,"timestampIso":"2023-05-10T11:57:16.000Z"},{"serialNumber":302,"code":0,"cities":["נתיבות"],"timestampSec":1683719839,"timestampMs":1683719839000,"timestampIso":"2023-05-10T11:57:19.000Z"},{"serialNumber":302,"code":0,"cities":["זמרת, שובה"],"timestampSec":1683719851,"timestampMs":1683719851000,"timestampIso":"2023-05-10T11:57:31.000Z"},{"serialNumber":302,"code":0,"cities":["תקומה"],"timestampSec":1683719853,"timestampMs":1683719853000,"timestampIso":"2023-05-10T11:57:33.000Z"},{"serialNumber":302,"code":8,"cities":["גפן","תירוש"],"timestampSec":1683719902,"timestampMs":1683719902000,"timestampIso":"2023-05-10T11:58:22.000Z"},{"serialNumber":302,"code":0,"cities":["נחל עוז","פארק תעשיות פלמחים","בית חנן","גן שורק","נטעים"],"timestampSec":1683719909,"timestampMs":1683719909000,"timestampIso":"2023-05-10T11:58:29.000Z"},{"serialNumber":302,"code":0,"cities":["בת ים","פלמחים","ראשון לציון - מערב"],"timestampSec":1683719941,"timestampMs":1683719941000,"timestampIso":"2023-05-10T11:59:01.000Z"},{"serialNumber":303,"code":0,"cities":["נתיב העשרה"],"timestampSec":1683720100,"timestampMs":1683720100000,"timestampIso":"2023-05-10T12:01:40.000Z"},{"serialNumber":303,"code":0,"cities":["מעגלים, גבעולים, מלילות","נתיבות","שרשרת"],"timestampSec":1683720142,"timestampMs":1683720142000,"timestampIso":"2023-05-10T12:02:22.000Z"},{"serialNumber":304,"code":0,"cities":["נחל עוז"],"timestampSec":1683720588,"timestampMs":1683720588000,"timestampIso":"2023-05-10T12:09:48.000Z"},{"serialNumber":305,"code":0,"cities":["ניר עם","שדרות, איבים"],"timestampSec":1683720780,"timestampMs":1683720780000,"timestampIso":"2023-05-10T12:13:00.000Z"},{"serialNumber":306,"code":0,"cities":["זיקים","נתיב העשרה"],"timestampSec":1683723222,"timestampMs":1683723222000,"timestampIso":"2023-05-10T12:53:42.000Z"},{"serialNumber":307,"code":0,"cities":["יד מרדכי"],"timestampSec":1683725793,"timestampMs":1683725793000,"timestampIso":"2023-05-10T13:36:33.000Z"},{"serialNumber":307,"code":0,"cities":["נתיב העשרה"],"timestampSec":1683725798,"timestampMs":1683725798000,"timestampIso":"2023-05-10T13:36:38.000Z"},{"serialNumber":308,"code":0,"cities":["נתיב העשרה"],"timestampSec":1683726854,"timestampMs":1683726854000,"timestampIso":"2023-05-10T13:54:14.000Z"},{"serialNumber":308,"code":0,"cities":["יד מרדכי"],"timestampSec":1683726859,"timestampMs":1683726859000,"timestampIso":"2023-05-10T13:54:19.000Z"},{"serialNumber":309,"code":0,"cities":["גן יבנה","חצור"],"timestampSec":1683728653,"timestampMs":1683728653000,"timestampIso":"2023-05-10T14:24:13.000Z"},{"serialNumber":309,"code":0,"cities":["עזריקם"],"timestampSec":1683728668,"timestampMs":1683728668000,"timestampIso":"2023-05-10T14:24:28.000Z"},{"serialNumber":309,"code":0,"cities":["גבעתי"],"timestampSec":1683728679,"timestampMs":1683728679000,"timestampIso":"2023-05-10T14:24:39.000Z"},{"serialNumber":310,"code":0,"cities":["כיסופים"],"timestampSec":1683734430,"timestampMs":1683734430000,"timestampIso":"2023-05-10T16:00:30.000Z"},{"serialNumber":311,"code":0,"cities":["מפלסים","מטווח ניר עם"],"timestampSec":1683736199,"timestampMs":1683736199000,"timestampIso":"2023-05-10T16:29:59.000Z"},{"serialNumber":311,"code":0,"cities":["ניר עם","שדרות, איבים"],"timestampSec":1683736202,"timestampMs":1683736202000,"timestampIso":"2023-05-10T16:30:02.000Z"},{"serialNumber":311,"code":0,"cities":["אזור תעשייה הדרומי אשקלון"],"timestampSec":1683736208,"timestampMs":1683736208000,"timestampIso":"2023-05-10T16:30:08.000Z"},{"serialNumber":311,"code":0,"cities":["זיקים","כרמיה"],"timestampSec":1683736211,"timestampMs":1683736211000,"timestampIso":"2023-05-10T16:30:11.000Z"},{"serialNumber":311,"code":0,"cities":["מבקיעים","אשקלון - דרום"],"timestampSec":1683736214,"timestampMs":1683736214000,"timestampIso":"2023-05-10T16:30:14.000Z"},{"serialNumber":311,"code":0,"cities":["נתיב העשרה"],"timestampSec":1683736226,"timestampMs":1683736226000,"timestampIso":"2023-05-10T16:30:26.000Z"},{"serialNumber":311,"code":0,"cities":["סופה"],"timestampSec":1683736231,"timestampMs":1683736231000,"timestampIso":"2023-05-10T16:30:31.000Z"},{"serialNumber":311,"code":0,"cities":["פלמחים"],"timestampSec":1683736265,"timestampMs":1683736265000,"timestampIso":"2023-05-10T16:31:05.000Z"},{"serialNumber":311,"code":0,"cities":["מטווח ניר עם"],"timestampSec":1683736297,"timestampMs":1683736297000,"timestampIso":"2023-05-10T16:31:37.000Z"},{"serialNumber":311,"code":0,"cities":["סופה"],"timestampSec":1683736313,"timestampMs":1683736313000,"timestampIso":"2023-05-10T16:31:53.000Z"},{"serialNumber":311,"code":0,"cities":["ניר עם","שדרות, איבים"],"timestampSec":1683736319,"timestampMs":1683736319000,"timestampIso":"2023-05-10T16:31:59.000Z"},{"serialNumber":311,"code":0,"cities":["אשדוד - איזור תעשייה צפוני"],"timestampSec":1683736331,"timestampMs":1683736331000,"timestampIso":"2023-05-10T16:32:11.000Z"},{"serialNumber":311,"code":0,"cities":["באר שבע - מערב","באר שבע - צפון"],"timestampSec":1683736352,"timestampMs":1683736352000,"timestampIso":"2023-05-10T16:32:32.000Z"},{"serialNumber":311,"code":0,"cities":["אזור תעשייה נ.ע.מ","בית הגדי","נתיבות","שרשרת"],"timestampSec":1683736354,"timestampMs":1683736354000,"timestampIso":"2023-05-10T16:32:34.000Z"},{"serialNumber":311,"code":0,"cities":["יושיביה"],"timestampSec":1683736374,"timestampMs":1683736374000,"timestampIso":"2023-05-10T16:32:54.000Z"},{"serialNumber":311,"code":0,"cities":["מבקיעים"],"timestampSec":1683736402,"timestampMs":1683736402000,"timestampIso":"2023-05-10T16:33:22.000Z"},{"serialNumber":311,"code":0,"cities":["אזור תעשייה הדרומי אשקלון"],"timestampSec":1683736404,"timestampMs":1683736404000,"timestampIso":"2023-05-10T16:33:24.000Z"},{"serialNumber":311,"code":0,"cities":["אזור תעשייה צפוני אשקלון","אשקלון - דרום","אשקלון - צפון","באר גנים"],"timestampSec":1683736416,"timestampMs":1683736416000,"timestampIso":"2023-05-10T16:33:36.000Z"},{"serialNumber":311,"code":0,"cities":["תל אביב - מזרח","אור יהודה","גבעת שמואל","גבעתיים","רמת גן - מזרח","רמת גן - מערב"],"timestampSec":1683736429,"timestampMs":1683736429000,"timestampIso":"2023-05-10T16:33:49.000Z"},{"serialNumber":311,"code":0,"cities":["אזור","גנות","חמד"],"timestampSec":1683736437,"timestampMs":1683736437000,"timestampIso":"2023-05-10T16:33:57.000Z"},{"serialNumber":311,"code":0,"cities":["בית דגן","חולון","מקווה ישראל","משמר השבעה","ראשון לציון - מזרח","ראשון לציון - מערב"],"timestampSec":1683736505,"timestampMs":1683736505000,"timestampIso":"2023-05-10T16:35:05.000Z"},{"serialNumber":311,"code":0,"cities":["מטווח ניר עם"],"timestampSec":1683736534,"timestampMs":1683736534000,"timestampIso":"2023-05-10T16:35:34.000Z"},{"serialNumber":311,"code":0,"cities":["ניר עם","שדרות, איבים"],"timestampSec":1683736535,"timestampMs":1683736535000,"timestampIso":"2023-05-10T16:35:35.000Z"},{"serialNumber":312,"code":0,"cities":["בית שקמה","גיאה","הודיה"],"timestampSec":1683736693,"timestampMs":1683736693000,"timestampIso":"2023-05-10T16:38:13.000Z"},{"serialNumber":313,"code":0,"cities":["עלומים"],"timestampSec":1683736817,"timestampMs":1683736817000,"timestampIso":"2023-05-10T16:40:17.000Z"},{"serialNumber":313,"code":0,"cities":["נחל עוז"],"timestampSec":1683736818,"timestampMs":1683736818000,"timestampIso":"2023-05-10T16:40:18.000Z"},{"serialNumber":314,"code":0,"cities":["חולית","סופה"],"timestampSec":1683737457,"timestampMs":1683737457000,"timestampIso":"2023-05-10T16:50:57.000Z"},{"serialNumber":315,"code":0,"cities":["ניר עם","שדרות, איבים"],"timestampSec":1683738383,"timestampMs":1683738383000,"timestampIso":"2023-05-10T17:06:23.000Z"},{"serialNumber":315,"code":0,"cities":["אור הנר"],"timestampSec":1683738394,"timestampMs":1683738394000,"timestampIso":"2023-05-10T17:06:34.000Z"},{"serialNumber":315,"code":0,"cities":["מטווח ניר עם"],"timestampSec":1683738406,"timestampMs":1683738406000,"timestampIso":"2023-05-10T17:06:46.000Z"},{"serialNumber":315,"code":0,"cities":["גבים, מכללת ספיר"],"timestampSec":1683738413,"timestampMs":1683738413000,"timestampIso":"2023-05-10T17:06:53.000Z"},{"serialNumber":316,"code":0,"cities":["ניר עם","שדרות, איבים"],"timestampSec":1683738528,"timestampMs":1683738528000,"timestampIso":"2023-05-10T17:08:48.000Z"},{"serialNumber":316,"code":0,"cities":["אור הנר"],"timestampSec":1683738548,"timestampMs":1683738548000,"timestampIso":"2023-05-10T17:09:08.000Z"},{"serialNumber":316,"code":0,"cities":["מטווח ניר עם"],"timestampSec":1683738581,"timestampMs":1683738581000,"timestampIso":"2023-05-10T17:09:41.000Z"},{"serialNumber":316,"code":0,"cities":["ניר עם","שדרות, איבים"],"timestampSec":1683738590,"timestampMs":1683738590000,"timestampIso":"2023-05-10T17:09:50.000Z"},{"serialNumber":317,"code":0,"cities":["זיקים"],"timestampSec":1683739674,"timestampMs":1683739674000,"timestampIso":"2023-05-10T17:27:54.000Z"},{"serialNumber":317,"code":0,"cities":["אזור תעשייה הדרומי אשקלון"],"timestampSec":1683739676,"timestampMs":1683739676000,"timestampIso":"2023-05-10T17:27:56.000Z"},{"serialNumber":318,"code":0,"cities":["מטווח ניר עם"],"timestampSec":1683739834,"timestampMs":1683739834000,"timestampIso":"2023-05-10T17:30:34.000Z"},{"serialNumber":319,"code":0,"cities":["ניר עם","שדרות, איבים"],"timestampSec":1683739936,"timestampMs":1683739936000,"timestampIso":"2023-05-10T17:32:16.000Z"},{"serialNumber":320,"code":0,"cities":["ניר עם","שדרות, איבים"],"timestampSec":1683741536,"timestampMs":1683741536000,"timestampIso":"2023-05-10T17:58:56.000Z"},{"serialNumber":321,"code":0,"cities":["אזור תעשייה הדרומי אשקלון"],"timestampSec":1683741707,"timestampMs":1683741707000,"timestampIso":"2023-05-10T18:01:47.000Z"},{"serialNumber":321,"code":0,"cities":["זיקים"],"timestampSec":1683741710,"timestampMs":1683741710000,"timestampIso":"2023-05-10T18:01:50.000Z"},{"serialNumber":321,"code":0,"cities":["נתיב העשרה"],"timestampSec":1683741712,"timestampMs":1683741712000,"timestampIso":"2023-05-10T18:01:52.000Z"},{"serialNumber":321,"code":0,"cities":["אשקלון - דרום"],"timestampSec":1683741729,"timestampMs":1683741729000,"timestampIso":"2023-05-10T18:02:09.000Z"},{"serialNumber":321,"code":0,"cities":["כרמיה"],"timestampSec":1683741736,"timestampMs":1683741736000,"timestampIso":"2023-05-10T18:02:16.000Z"},{"serialNumber":322,"code":0,"cities":["זמרת, שובה"],"timestampSec":1683741897,"timestampMs":1683741897000,"timestampIso":"2023-05-10T18:04:57.000Z"},{"serialNumber":322,"code":0,"cities":["כפר מימון ותושיה","נתיבות","סעד","עלומים"],"timestampSec":1683741903,"timestampMs":1683741903000,"timestampIso":"2023-05-10T18:05:03.000Z"},{"serialNumber":322,"code":0,"cities":["כפר עזה"],"timestampSec":1683741909,"timestampMs":1683741909000,"timestampIso":"2023-05-10T18:05:09.000Z"},{"serialNumber":322,"code":0,"cities":["בית הגדי"],"timestampSec":1683741916,"timestampMs":1683741916000,"timestampIso":"2023-05-10T18:05:16.000Z"},{"serialNumber":322,"code":0,"cities":["שוקדה"],"timestampSec":1683741928,"timestampMs":1683741928000,"timestampIso":"2023-05-10T18:05:28.000Z"},{"serialNumber":322,"code":0,"cities":["תקומה"],"timestampSec":1683741930,"timestampMs":1683741930000,"timestampIso":"2023-05-10T18:05:30.000Z"},{"serialNumber":323,"code":0,"cities":["ניר עם","שדרות, איבים"],"timestampSec":1683742187,"timestampMs":1683742187000,"timestampIso":"2023-05-10T18:09:47.000Z"},{"serialNumber":323,"code":0,"cities":["גבים, מכללת ספיר"],"timestampSec":1683742189,"timestampMs":1683742189000,"timestampIso":"2023-05-10T18:09:49.000Z"},{"serialNumber":324,"code":0,"cities":["כפר מימון ותושיה"],"timestampSec":1683747065,"timestampMs":1683747065000,"timestampIso":"2023-05-10T19:31:05.000Z"},{"serialNumber":325,"code":0,"cities":["סופה"],"timestampSec":1683752139,"timestampMs":1683752139000,"timestampIso":"2023-05-10T20:55:39.000Z"}]}