{"day":"2024-04-25","count":2,"from":"2024-04-25T12:24:50.000Z","to":"2024-04-25T12:35:34.000Z","alerts":[{"serialNumber":2501,"code":0,"cities":["ערב אל עראמשה"],"timestampSec":1714047890,"timestampMs":1714047890000,"timestampIso":"2024-04-25T12:24:50.000Z"},{"serialNumber":2502,"code":5,"cities":["קריית שמונה","מרגליות","משגב עם","מעיין ברוך","תל חי","כפר גלעדי","מטולה","מנרה","כפר יובל","בית הלל"],"timestampSec":1714048534,"timestampMs":1714048534000,"timestampIso":"2024-04-25T12:35:34.000Z"}]}