{"day":"2024-10-15","count":68,"from":"2024-10-15T02:32:12.000Z","to":"2024-10-15T23:32:09.000Z","alerts":[{"serialNumber":4285,"code":0,"cities":["קריית שמונה"],"timestampSec":1728959532,"timestampMs":1728959532000,"timestampIso":"2024-10-15T02:32:12.000Z"},{"serialNumber":4285,"code":0,"cities":["בית הלל","הגושרים"],"timestampSec":1728959537,"timestampMs":1728959537000,"timestampIso":"2024-10-15T02:32:17.000Z"},{"serialNumber":4285,"code":0,"cities":["כפר יובל","מעיין ברוך"],"timestampSec":1728959546,"timestampMs":1728959546000,"timestampIso":"2024-10-15T02:32:26.000Z"},{"serialNumber":4286,"code":0,"cities":["כפר גלעדי","משגב עם"],"timestampSec":1728960983,"timestampMs":1728960983000,"timestampIso":"2024-10-15T02:56:23.000Z"},{"serialNumber":4287,"code":0,"cities":["זכרון יעקב","מעגן מיכאל","מעיין צבי"],"timestampSec":1728966298,"timestampMs":1728966298000,"timestampIso":"2024-10-15T04:24:58.000Z"},{"serialNumber":4287,"code":0,"cities":["גבעת וולפסון","דלית אל כרמל","אזור תעשייה ניר עציון","גבע כרמל","דור","הבונים","כפר הנוער ימין אורד","כרם מהר''ל","מאיר שפיה","מרכז מיר''ב","נווה ים","נחשולים","ניר עציון","עופר","עין איילה","עין הוד","עין חוד","עין כרמל","עתלית","פוריידיס","צרופה","יערות הכרמל"],"timestampSec":1728966300,"timestampMs":1728966300000,"timestampIso":"2024-10-15T04:25:00.000Z"},{"serialNumber":4287,"code":0,"cities":["תלמי אלעזר"],"timestampSec":1728966327,"timestampMs":1728966327000,"timestampIso":"2024-10-15T04:25:27.000Z"},{"serialNumber":4288,"code":0,"cities":["בית אורן","גבעת וולפסון","דלית אל כרמל","אזור תעשייה ניר עציון","בית צבי","בת שלמה","גבע כרמל","דור","הבונים","כפר הנוער ימין אורד","כרם מהר''ל","מאיר שפיה","מגדים","מרכז מיר''ב","נווה ים","נחשולים","ניר עציון","עופר","עין איילה","עין הוד","עין חוד","עין כרמל","עתלית","פוריידיס","צרופה","יערות הכרמל","אביאל","אור עקיבא","אזור תעשייה מבוא כרמל","אזור תעשייה קיסריה","אלוני יצחק","אליקים","בית חנניה","בנימינה","ג'סר א-זרקא","גבעת ניל''י","גבעת עדה","דליה","יקנעם עילית","כפר גליקסון","עמיקם","פרדס חנה כרכור","קיסריה","רמות מנשה","שדות ים","צומת בנימינה","אזור תעשייה רגבים","בית ספר אורט בנימינה","מרכז ימי קיסריה","רמת הנדיב"],"timestampSec":1728966425,"timestampMs":1728966425000,"timestampIso":"2024-10-15T04:27:05.000Z"},{"serialNumber":4288,"code":0,"cities":["אושה","חיפה - כרמל, הדר ועיר תחתית","חיפה - מערב","חיפה - מפרץ","חיפה - נווה שאנן ורמות כרמל","חיפה - קריית חיים ושמואל","כפר ביאליק","כפר המכבי","קריית אתא","קריית ביאליק","קריית ים","קריית מוצקין","רמת יוחנן","נשר","אורנים","איבטין","אלונים","בסמת טבעון","החותרים","טירת כרמל","יגור","כפר גלים","כפר חסידים","כפר טבאש","כפר יהושע","כפר תקווה","נופית","עספיא","קריית טבעון - בית זייד","ראס עלי","רכסים","רמת ישי","שדה יעקב","שער העמקים","בית סוהר קישון","בית עלמין תל רגב","ח'וואלד","חוואלד","כלא דמון","תחנת רכבת כפר יהושוע","אזור תעשייה יקנעם עילית","יקנעם המושבה והזורע","עין העמק"],"timestampSec":1728966472,"timestampMs":1728966472000,"timestampIso":"2024-10-15T04:27:52.000Z"},{"serialNumber":4289,"code":0,"cities":["משגב עם"],"timestampSec":1728966594,"timestampMs":1728966594000,"timestampIso":"2024-10-15T04:29:54.000Z"},{"serialNumber":4290,"code":0,"cities":["משגב עם"],"timestampSec":1728975263,"timestampMs":1728975263000,"timestampIso":"2024-10-15T06:54:23.000Z"},{"serialNumber":4290,"code":0,"cities":["כפר גלעדי"],"timestampSec":1728975268,"timestampMs":1728975268000,"timestampIso":"2024-10-15T06:54:28.000Z"},{"serialNumber":4290,"code":0,"cities":["קריית שמונה"],"timestampSec":1728975269,"timestampMs":1728975269000,"timestampIso":"2024-10-15T06:54:29.000Z"},{"serialNumber":4290,"code":0,"cities":["משגב עם"],"timestampSec":1728975313,"timestampMs":1728975313000,"timestampIso":"2024-10-15T06:55:13.000Z"},{"serialNumber":4291,"code":0,"cities":["קריית ביאליק"],"timestampSec":1728991206,"timestampMs":1728991206000,"timestampIso":"2024-10-15T11:20:06.000Z"},{"serialNumber":4291,"code":0,"cities":["קריית ים","קריית מוצקין","אזור תעשייה קריית ביאליק"],"timestampSec":1728991208,"timestampMs":1728991208000,"timestampIso":"2024-10-15T11:20:08.000Z"},{"serialNumber":4291,"code":0,"cities":["אזור תעשייה שער נעמן"],"timestampSec":1728991213,"timestampMs":1728991213000,"timestampIso":"2024-10-15T11:20:13.000Z"},{"serialNumber":4291,"code":0,"cities":["חיפה - קריית חיים ושמואל"],"timestampSec":1728991218,"timestampMs":1728991218000,"timestampIso":"2024-10-15T11:20:18.000Z"},{"serialNumber":4291,"code":0,"cities":["חיפה - מפרץ","כפר ביאליק","קריית אתא"],"timestampSec":1728991227,"timestampMs":1728991227000,"timestampIso":"2024-10-15T11:20:27.000Z"},{"serialNumber":4291,"code":0,"cities":["אפק"],"timestampSec":1728991242,"timestampMs":1728991242000,"timestampIso":"2024-10-15T11:20:42.000Z"},{"serialNumber":4291,"code":0,"cities":["כפר מסריק"],"timestampSec":1728991254,"timestampMs":1728991254000,"timestampIso":"2024-10-15T11:20:54.000Z"},{"serialNumber":4291,"code":0,"cities":["עין המפרץ","עכו - אזור תעשייה"],"timestampSec":1728991258,"timestampMs":1728991258000,"timestampIso":"2024-10-15T11:20:58.000Z"},{"serialNumber":4292,"code":0,"cities":["מטולה"],"timestampSec":1728991463,"timestampMs":1728991463000,"timestampIso":"2024-10-15T11:24:23.000Z"},{"serialNumber":4293,"code":5,"cities":["נהריה","סער"],"timestampSec":1728991827,"timestampMs":1728991827000,"timestampIso":"2024-10-15T11:30:27.000Z"},{"serialNumber":4293,"code":0,"cities":["גשר הזיו"],"timestampSec":1728991861,"timestampMs":1728991861000,"timestampIso":"2024-10-15T11:31:01.000Z"},{"serialNumber":4293,"code":5,"cities":["כברי"],"timestampSec":1728991876,"timestampMs":1728991876000,"timestampIso":"2024-10-15T11:31:16.000Z"},{"serialNumber":4293,"code":5,"cities":["בית העלמין החדש נהריה","נתיב השיירה"],"timestampSec":1728991878,"timestampMs":1728991878000,"timestampIso":"2024-10-15T11:31:18.000Z"},{"serialNumber":4294,"code":0,"cities":["דוב''ב"],"timestampSec":1728993161,"timestampMs":1728993161000,"timestampIso":"2024-10-15T11:52:41.000Z"},{"serialNumber":4295,"code":0,"cities":["חורפיש"],"timestampSec":1728997827,"timestampMs":1728997827000,"timestampIso":"2024-10-15T13:10:27.000Z"},{"serialNumber":4295,"code":0,"cities":["מתת"],"timestampSec":1728997836,"timestampMs":1728997836000,"timestampIso":"2024-10-15T13:10:36.000Z"},{"serialNumber":4296,"code":0,"cities":["ביריה"],"timestampSec":1729005601,"timestampMs":1729005601000,"timestampIso":"2024-10-15T15:20:01.000Z"},{"serialNumber":4297,"code":0,"cities":["שאר ישוב"],"timestampSec":1729007460,"timestampMs":1729007460000,"timestampIso":"2024-10-15T15:51:00.000Z"},{"serialNumber":4298,"code":0,"cities":["חזון","מע'אר"],"timestampSec":1729008129,"timestampMs":1729008129000,"timestampIso":"2024-10-15T16:02:09.000Z"},{"serialNumber":4298,"code":0,"cities":["מורן"],"timestampSec":1729008131,"timestampMs":1729008131000,"timestampIso":"2024-10-15T16:02:11.000Z"},{"serialNumber":4298,"code":0,"cities":["טורעאן"],"timestampSec":1729008142,"timestampMs":1729008142000,"timestampIso":"2024-10-15T16:02:22.000Z"},{"serialNumber":4298,"code":0,"cities":["אילניה","מצפה נטופה"],"timestampSec":1729008150,"timestampMs":1729008150000,"timestampIso":"2024-10-15T16:02:30.000Z"},{"serialNumber":4298,"code":0,"cities":["אתר ההנצחה גולני"],"timestampSec":1729008151,"timestampMs":1729008151000,"timestampIso":"2024-10-15T16:02:31.000Z"},{"serialNumber":4298,"code":0,"cities":["בועיינה-נוג'ידאת"],"timestampSec":1729008171,"timestampMs":1729008171000,"timestampIso":"2024-10-15T16:02:51.000Z"},{"serialNumber":4299,"code":0,"cities":["טורעאן"],"timestampSec":1729008300,"timestampMs":1729008300000,"timestampIso":"2024-10-15T16:05:00.000Z"},{"serialNumber":4300,"code":0,"cities":["מתת"],"timestampSec":1729011637,"timestampMs":1729011637000,"timestampIso":"2024-10-15T17:00:37.000Z"},{"serialNumber":4300,"code":0,"cities":["בית ג'אן","ראמה"],"timestampSec":1729011674,"timestampMs":1729011674000,"timestampIso":"2024-10-15T17:01:14.000Z"},{"serialNumber":4301,"code":0,"cities":["ראש הנקרה"],"timestampSec":1729014993,"timestampMs":1729014993000,"timestampIso":"2024-10-15T17:56:33.000Z"},{"serialNumber":4301,"code":0,"cities":["שלומי"],"timestampSec":1729014994,"timestampMs":1729014994000,"timestampIso":"2024-10-15T17:56:34.000Z"},{"serialNumber":4301,"code":0,"cities":["חוף בצת"],"timestampSec":1729015009,"timestampMs":1729015009000,"timestampIso":"2024-10-15T17:56:49.000Z"},{"serialNumber":4302,"code":0,"cities":["נטועה","שתולה"],"timestampSec":1729019188,"timestampMs":1729019188000,"timestampIso":"2024-10-15T19:06:28.000Z"},{"serialNumber":4303,"code":0,"cities":["נירים"],"timestampSec":1729021383,"timestampMs":1729021383000,"timestampIso":"2024-10-15T19:43:03.000Z"},{"serialNumber":4304,"code":0,"cities":["יערה"],"timestampSec":1729025447,"timestampMs":1729025447000,"timestampIso":"2024-10-15T20:50:47.000Z"},{"serialNumber":4305,"code":0,"cities":["כפר סאלד"],"timestampSec":1729026630,"timestampMs":1729026630000,"timestampIso":"2024-10-15T21:10:30.000Z"},{"serialNumber":4305,"code":0,"cities":["שאר ישוב"],"timestampSec":1729026639,"timestampMs":1729026639000,"timestampIso":"2024-10-15T21:10:39.000Z"},{"serialNumber":4306,"code":5,"cities":["כפר יובל"],"timestampSec":1729027293,"timestampMs":1729027293000,"timestampIso":"2024-10-15T21:21:33.000Z"},{"serialNumber":4306,"code":5,"cities":["כפר גלעדי"],"timestampSec":1729027319,"timestampMs":1729027319000,"timestampIso":"2024-10-15T21:21:59.000Z"},{"serialNumber":4307,"code":0,"cities":["צפת - נוף כנרת"],"timestampSec":1729031936,"timestampMs":1729031936000,"timestampIso":"2024-10-15T22:38:56.000Z"},{"serialNumber":4307,"code":0,"cities":["צפת - עיר"],"timestampSec":1729031938,"timestampMs":1729031938000,"timestampIso":"2024-10-15T22:38:58.000Z"},{"serialNumber":4307,"code":0,"cities":["אזור תעשייה רמת דלתון","דלתון","עלמה","ריחאנייה"],"timestampSec":1729031940,"timestampMs":1729031940000,"timestampIso":"2024-10-15T22:39:00.000Z"},{"serialNumber":4307,"code":0,"cities":["ביריה","עמוקה"],"timestampSec":1729031944,"timestampMs":1729031944000,"timestampIso":"2024-10-15T22:39:04.000Z"},{"serialNumber":4307,"code":0,"cities":["צפת - עכברה"],"timestampSec":1729031948,"timestampMs":1729031948000,"timestampIso":"2024-10-15T22:39:08.000Z"},{"serialNumber":4307,"code":0,"cities":["כרם בן זמרה"],"timestampSec":1729031955,"timestampMs":1729031955000,"timestampIso":"2024-10-15T22:39:15.000Z"},{"serialNumber":4307,"code":0,"cities":["חצור הגלילית","ראש פינה"],"timestampSec":1729031968,"timestampMs":1729031968000,"timestampIso":"2024-10-15T22:39:28.000Z"},{"serialNumber":4307,"code":0,"cities":["צפת - נוף כנרת"],"timestampSec":1729031976,"timestampMs":1729031976000,"timestampIso":"2024-10-15T22:39:36.000Z"},{"serialNumber":4307,"code":0,"cities":["צפת - עיר"],"timestampSec":1729031978,"timestampMs":1729031978000,"timestampIso":"2024-10-15T22:39:38.000Z"},{"serialNumber":4307,"code":0,"cities":["אזור תעשייה רמת דלתון","עלמה","ריחאנייה"],"timestampSec":1729031983,"timestampMs":1729031983000,"timestampIso":"2024-10-15T22:39:43.000Z"},{"serialNumber":4307,"code":0,"cities":["אליפלט"],"timestampSec":1729031995,"timestampMs":1729031995000,"timestampIso":"2024-10-15T22:39:55.000Z"},{"serialNumber":4307,"code":0,"cities":["ביריה","עמוקה"],"timestampSec":1729031996,"timestampMs":1729031996000,"timestampIso":"2024-10-15T22:39:56.000Z"},{"serialNumber":4307,"code":0,"cities":["צפת - עכברה"],"timestampSec":1729032000,"timestampMs":1729032000000,"timestampIso":"2024-10-15T22:40:00.000Z"},{"serialNumber":4307,"code":0,"cities":["חצור הגלילית","ראש פינה"],"timestampSec":1729032018,"timestampMs":1729032018000,"timestampIso":"2024-10-15T22:40:18.000Z"},{"serialNumber":4307,"code":0,"cities":["צפת - נוף כנרת","צפת - עיר"],"timestampSec":1729032023,"timestampMs":1729032023000,"timestampIso":"2024-10-15T22:40:23.000Z"},{"serialNumber":4308,"code":0,"cities":["דישון"],"timestampSec":1729034955,"timestampMs":1729034955000,"timestampIso":"2024-10-15T23:29:15.000Z"},{"serialNumber":4309,"code":0,"cities":["אור הגנוז","בר יוחאי","ג'ש - גוש חלב","ספסופה - כפר חושן"],"timestampSec":1729035129,"timestampMs":1729035129000,"timestampIso":"2024-10-15T23:32:09.000Z"}]}