{"day":"2025-08-05","count":2,"from":"2025-08-04T22:00:36.000Z","to":"2025-08-04T22:01:38.000Z","alerts":[{"serialNumber":5526,"code":0,"cities":["כפר דניאל","גמזו","כפר רות","לפיד","מבוא חורון","מבוא מודיעים","מודיעין - ליגד סנטר","מודיעין מכבים רעות","נוף איילון","שילת","שעלבים","יד בנימין","מעלה החמישה","צובה","קריית ענבים","אזור תעשייה רבדים","מפעל אגריגדה","אביעזר","אזור תעשייה הר טוב - צרעה","אשתאול","בית חשמונאי","בית עוזיאל","בית שמש","בקוע","גזר","גיזו","גני הדר","גני יוחנן","הראל","זנוח","חולדה","טל שחר","יד רמב''ם","יסודות","יציץ","ישעי","כפר אוריה","כפר בן נון","כפר שמואל","כרמי יוסף","לטרון","מזכרת בתיה","מחסיה","מיני ישראל - נחשון","מסילת ציון","משמר איילון","משמר דוד","נווה שלום","נחם","נחשון","נען","נצר חזני","נתיב הל''ה","עזריה","פדיה","פתחיה","צלפון","צרעה","רטורנו - גבעת שמש","רמות מאיר","שער הגיא","תעוז","תרום","גפן","זכריה","עגור","שדות מיכה","תירוש","אבו גוש","בית מאיר","בר גיורא","גבעת יערים","יד השמונה","כסלון","כפר הנוער קריית יערים","מטע","נווה אילן","נטף","נס הרים","עין ראפה","קריית יערים","רמת רזיאל","שואבה","שורש","צומת האלה","אזור תעשייה ברוש","כפר האורנים","מודיעין - ישפרו סנטר"],"timestampSec":1754344836,"timestampMs":1754344836000,"timestampIso":"2025-08-04T22:00:36.000Z"},{"serialNumber":5526,"code":0,"cities":["בית אלעזרי","בית חלקיה","בני ראם","גני טל","חפץ חיים","כפר מנחם","קדרון","רבדים","כפר ביל''ו","סתריה","קריית עקרון","תחנת רכבת קריית מלאכי - יואב","לוזית","שריגים - לי-און","גבעת ישעיהו"],"timestampSec":1754344898,"timestampMs":1754344898000,"timestampIso":"2025-08-04T22:01:38.000Z"}]}