{"day":"2026-04-13","count":130,"from":"2026-04-12T22:19:52.000Z","to":"2026-04-13T19:55:47.000Z","alerts":[{"serialNumber":7268,"code":0,"cities":["קריית שמונה","בית הלל"],"timestampSec":1776032392,"timestampMs":1776032392000,"timestampIso":"2026-04-12T22:19:52.000Z"},{"serialNumber":7268,"code":0,"cities":["מטולה","משגב עם"],"timestampSec":1776032406,"timestampMs":1776032406000,"timestampIso":"2026-04-12T22:20:06.000Z"},{"serialNumber":7268,"code":0,"cities":["כפר גלעדי","כפר יובל","מעיין ברוך","תל חי"],"timestampSec":1776032415,"timestampMs":1776032415000,"timestampIso":"2026-04-12T22:20:15.000Z"},{"serialNumber":7268,"code":0,"cities":["בית הלל"],"timestampSec":1776032432,"timestampMs":1776032432000,"timestampIso":"2026-04-12T22:20:32.000Z"},{"serialNumber":7268,"code":0,"cities":["מטולה"],"timestampSec":1776032445,"timestampMs":1776032445000,"timestampIso":"2026-04-12T22:20:45.000Z"},{"serialNumber":7268,"code":0,"cities":["כפר יובל"],"timestampSec":1776032454,"timestampMs":1776032454000,"timestampIso":"2026-04-12T22:20:54.000Z"},{"serialNumber":7269,"code":0,"cities":["דוב''ב"],"timestampSec":1776037783,"timestampMs":1776037783000,"timestampIso":"2026-04-12T23:49:43.000Z"},{"serialNumber":7270,"code":5,"cities":["מטולה"],"timestampSec":1776056165,"timestampMs":1776056165000,"timestampIso":"2026-04-13T04:56:05.000Z"},{"serialNumber":7270,"code":5,"cities":["משגב עם"],"timestampSec":1776056221,"timestampMs":1776056221000,"timestampIso":"2026-04-13T04:57:01.000Z"},{"serialNumber":7271,"code":5,"cities":["ראש הנקרה"],"timestampSec":1776058653,"timestampMs":1776058653000,"timestampIso":"2026-04-13T05:37:33.000Z"},{"serialNumber":7271,"code":5,"cities":["שלומי"],"timestampSec":1776058700,"timestampMs":1776058700000,"timestampIso":"2026-04-13T05:38:20.000Z"},{"serialNumber":7272,"code":5,"cities":["משגב עם"],"timestampSec":1776066862,"timestampMs":1776066862000,"timestampIso":"2026-04-13T07:54:22.000Z"},{"serialNumber":7273,"code":5,"cities":["קריית שמונה"],"timestampSec":1776067354,"timestampMs":1776067354000,"timestampIso":"2026-04-13T08:02:34.000Z"},{"serialNumber":7273,"code":5,"cities":["מנרה"],"timestampSec":1776067363,"timestampMs":1776067363000,"timestampIso":"2026-04-13T08:02:43.000Z"},{"serialNumber":7273,"code":5,"cities":["מרגליות","משגב עם"],"timestampSec":1776067617,"timestampMs":1776067617000,"timestampIso":"2026-04-13T08:06:57.000Z"},{"serialNumber":7273,"code":5,"cities":["קריית שמונה"],"timestampSec":1776067645,"timestampMs":1776067645000,"timestampIso":"2026-04-13T08:07:25.000Z"},{"serialNumber":7273,"code":5,"cities":["כפר גלעדי"],"timestampSec":1776067646,"timestampMs":1776067646000,"timestampIso":"2026-04-13T08:07:26.000Z"},{"serialNumber":7273,"code":5,"cities":["מנרה"],"timestampSec":1776067655,"timestampMs":1776067655000,"timestampIso":"2026-04-13T08:07:35.000Z"},{"serialNumber":7273,"code":0,"cities":["משגב עם"],"timestampSec":1776067659,"timestampMs":1776067659000,"timestampIso":"2026-04-13T08:07:39.000Z"},{"serialNumber":7273,"code":5,"cities":["תל חי"],"timestampSec":1776067683,"timestampMs":1776067683000,"timestampIso":"2026-04-13T08:08:03.000Z"},{"serialNumber":7273,"code":5,"cities":["משגב עם"],"timestampSec":1776067699,"timestampMs":1776067699000,"timestampIso":"2026-04-13T08:08:19.000Z"},{"serialNumber":7273,"code":0,"cities":["קריית שמונה","תל חי"],"timestampSec":1776067758,"timestampMs":1776067758000,"timestampIso":"2026-04-13T08:09:18.000Z"},{"serialNumber":7273,"code":0,"cities":["כפר גלעדי"],"timestampSec":1776067766,"timestampMs":1776067766000,"timestampIso":"2026-04-13T08:09:26.000Z"},{"serialNumber":7273,"code":5,"cities":["כפר יובל"],"timestampSec":1776067787,"timestampMs":1776067787000,"timestampIso":"2026-04-13T08:09:47.000Z"},{"serialNumber":7273,"code":5,"cities":["קריית שמונה","תל חי"],"timestampSec":1776067793,"timestampMs":1776067793000,"timestampIso":"2026-04-13T08:09:53.000Z"},{"serialNumber":7273,"code":5,"cities":["כפר גלעדי"],"timestampSec":1776067801,"timestampMs":1776067801000,"timestampIso":"2026-04-13T08:10:01.000Z"},{"serialNumber":7273,"code":5,"cities":["מעיין ברוך"],"timestampSec":1776067807,"timestampMs":1776067807000,"timestampIso":"2026-04-13T08:10:07.000Z"},{"serialNumber":7273,"code":5,"cities":["בית הלל"],"timestampSec":1776067809,"timestampMs":1776067809000,"timestampIso":"2026-04-13T08:10:09.000Z"},{"serialNumber":7273,"code":0,"cities":["כפר גלעדי","קריית שמונה","תל חי"],"timestampSec":1776067813,"timestampMs":1776067813000,"timestampIso":"2026-04-13T08:10:13.000Z"},{"serialNumber":7273,"code":5,"cities":["הגושרים"],"timestampSec":1776067827,"timestampMs":1776067827000,"timestampIso":"2026-04-13T08:10:27.000Z"},{"serialNumber":7273,"code":5,"cities":["כפר גלעדי","קריית שמונה","תל חי"],"timestampSec":1776067849,"timestampMs":1776067849000,"timestampIso":"2026-04-13T08:10:49.000Z"},{"serialNumber":7274,"code":5,"cities":["אביבים"],"timestampSec":1776068300,"timestampMs":1776068300000,"timestampIso":"2026-04-13T08:18:20.000Z"},{"serialNumber":7275,"code":5,"cities":["אבן מנחם","זרעית","שומרה","שתולה"],"timestampSec":1776070198,"timestampMs":1776070198000,"timestampIso":"2026-04-13T08:49:58.000Z"},{"serialNumber":7275,"code":0,"cities":["משגב עם"],"timestampSec":1776070198,"timestampMs":1776070198000,"timestampIso":"2026-04-13T08:49:58.000Z"},{"serialNumber":7275,"code":0,"cities":["כפר גלעדי"],"timestampSec":1776070211,"timestampMs":1776070211000,"timestampIso":"2026-04-13T08:50:11.000Z"},{"serialNumber":7276,"code":0,"cities":["משגב עם"],"timestampSec":1776070472,"timestampMs":1776070472000,"timestampIso":"2026-04-13T08:54:32.000Z"},{"serialNumber":7276,"code":0,"cities":["מרגליות"],"timestampSec":1776070474,"timestampMs":1776070474000,"timestampIso":"2026-04-13T08:54:34.000Z"},{"serialNumber":7277,"code":5,"cities":["נטועה","שתולה"],"timestampSec":1776071486,"timestampMs":1776071486000,"timestampIso":"2026-04-13T09:11:26.000Z"},{"serialNumber":7277,"code":5,"cities":["לב החולה","אביבים","אור הגנוז","אזור תעשייה רמת דלתון","בר יוחאי","ברעם","ג'ש - גוש חלב","דוב''ב","דישון","דלתון","יסוד המעלה","יפתח","יראון","כפר בלום","כרם בן זמרה","מירון","מלכיה","מרכז אזורי מבואות חרמון","מרכז אזורי מרום גליל","נאות מרדכי","סאסא","ספסופה - כפר חושן","עלמה","עמוקה","צבעון","קדיתא","ריחאנייה","רמות נפתלי","שדה אליעזר"],"timestampSec":1776071600,"timestampMs":1776071600000,"timestampIso":"2026-04-13T09:13:20.000Z"},{"serialNumber":7277,"code":5,"cities":["חוף בצת","ראש הנקרה","שלומי"],"timestampSec":1776071906,"timestampMs":1776071906000,"timestampIso":"2026-04-13T09:18:26.000Z"},{"serialNumber":7277,"code":5,"cities":["בצת"],"timestampSec":1776071913,"timestampMs":1776071913000,"timestampIso":"2026-04-13T09:18:33.000Z"},{"serialNumber":7277,"code":5,"cities":["איזור תעשייה מילואות צפון"],"timestampSec":1776071917,"timestampMs":1776071917000,"timestampIso":"2026-04-13T09:18:37.000Z"},{"serialNumber":7277,"code":5,"cities":["לימן"],"timestampSec":1776071929,"timestampMs":1776071929000,"timestampIso":"2026-04-13T09:18:49.000Z"},{"serialNumber":7277,"code":5,"cities":["חוף אכזיב"],"timestampSec":1776071941,"timestampMs":1776071941000,"timestampIso":"2026-04-13T09:19:01.000Z"},{"serialNumber":7277,"code":5,"cities":["גשר הזיו"],"timestampSec":1776071980,"timestampMs":1776071980000,"timestampIso":"2026-04-13T09:19:40.000Z"},{"serialNumber":7277,"code":5,"cities":["נהריה"],"timestampSec":1776071985,"timestampMs":1776071985000,"timestampIso":"2026-04-13T09:19:45.000Z"},{"serialNumber":7277,"code":5,"cities":["סער"],"timestampSec":1776072005,"timestampMs":1776072005000,"timestampIso":"2026-04-13T09:20:05.000Z"},{"serialNumber":7277,"code":5,"cities":["לימן"],"timestampSec":1776072111,"timestampMs":1776072111000,"timestampIso":"2026-04-13T09:21:51.000Z"},{"serialNumber":7277,"code":5,"cities":["חוף אכזיב"],"timestampSec":1776072121,"timestampMs":1776072121000,"timestampIso":"2026-04-13T09:22:01.000Z"},{"serialNumber":7277,"code":5,"cities":["גשר הזיו","נהריה","סער"],"timestampSec":1776072209,"timestampMs":1776072209000,"timestampIso":"2026-04-13T09:23:29.000Z"},{"serialNumber":7277,"code":5,"cities":["בוסתן הגליל","עכו","שבי ציון","שמרת","לוחמי הגטאות","רגבה"],"timestampSec":1776072407,"timestampMs":1776072407000,"timestampIso":"2026-04-13T09:26:47.000Z"},{"serialNumber":7277,"code":5,"cities":["עכו - רמות ים"],"timestampSec":1776072423,"timestampMs":1776072423000,"timestampIso":"2026-04-13T09:27:03.000Z"},{"serialNumber":7277,"code":5,"cities":["עכו - אזור תעשייה"],"timestampSec":1776072485,"timestampMs":1776072485000,"timestampIso":"2026-04-13T09:28:05.000Z"},{"serialNumber":7277,"code":5,"cities":["עין המפרץ"],"timestampSec":1776072496,"timestampMs":1776072496000,"timestampIso":"2026-04-13T09:28:16.000Z"},{"serialNumber":7277,"code":5,"cities":["כפר מסריק"],"timestampSec":1776072521,"timestampMs":1776072521000,"timestampIso":"2026-04-13T09:28:41.000Z"},{"serialNumber":7277,"code":5,"cities":["אזור תעשייה שער נעמן"],"timestampSec":1776072551,"timestampMs":1776072551000,"timestampIso":"2026-04-13T09:29:11.000Z"},{"serialNumber":7277,"code":5,"cities":["ג'דידה מכר"],"timestampSec":1776072575,"timestampMs":1776072575000,"timestampIso":"2026-04-13T09:29:35.000Z"},{"serialNumber":7277,"code":5,"cities":["אזור תעשייה קריית ביאליק"],"timestampSec":1776072585,"timestampMs":1776072585000,"timestampIso":"2026-04-13T09:29:45.000Z"},{"serialNumber":7277,"code":5,"cities":["עכו"],"timestampSec":1776072587,"timestampMs":1776072587000,"timestampIso":"2026-04-13T09:29:47.000Z"},{"serialNumber":7277,"code":5,"cities":["קריית ים"],"timestampSec":1776072610,"timestampMs":1776072610000,"timestampIso":"2026-04-13T09:30:10.000Z"},{"serialNumber":7277,"code":5,"cities":["קריית ביאליק","קריית מוצקין"],"timestampSec":1776072613,"timestampMs":1776072613000,"timestampIso":"2026-04-13T09:30:13.000Z"},{"serialNumber":7277,"code":0,"cities":["דוב''ב"],"timestampSec":1776072668,"timestampMs":1776072668000,"timestampIso":"2026-04-13T09:31:08.000Z"},{"serialNumber":7277,"code":0,"cities":["אביבים"],"timestampSec":1776072672,"timestampMs":1776072672000,"timestampIso":"2026-04-13T09:31:12.000Z"},{"serialNumber":7277,"code":0,"cities":["יראון"],"timestampSec":1776072688,"timestampMs":1776072688000,"timestampIso":"2026-04-13T09:31:28.000Z"},{"serialNumber":7277,"code":5,"cities":["אפק"],"timestampSec":1776072715,"timestampMs":1776072715000,"timestampIso":"2026-04-13T09:31:55.000Z"},{"serialNumber":7278,"code":0,"cities":["מרגליות"],"timestampSec":1776073376,"timestampMs":1776073376000,"timestampIso":"2026-04-13T09:42:56.000Z"},{"serialNumber":7278,"code":0,"cities":["משגב עם"],"timestampSec":1776073394,"timestampMs":1776073394000,"timestampIso":"2026-04-13T09:43:14.000Z"},{"serialNumber":7279,"code":0,"cities":["זרעית"],"timestampSec":1776074234,"timestampMs":1776074234000,"timestampIso":"2026-04-13T09:57:14.000Z"},{"serialNumber":7279,"code":0,"cities":["שומרה"],"timestampSec":1776074245,"timestampMs":1776074245000,"timestampIso":"2026-04-13T09:57:25.000Z"},{"serialNumber":7279,"code":0,"cities":["שתולה"],"timestampSec":1776074275,"timestampMs":1776074275000,"timestampIso":"2026-04-13T09:57:55.000Z"},{"serialNumber":7280,"code":0,"cities":["כרמיאל","בענה","דיר אל-אסד","כישור","מג'דל כרום","צורית גילון","פלך","תובל"],"timestampSec":1776074650,"timestampMs":1776074650000,"timestampIso":"2026-04-13T10:04:10.000Z"},{"serialNumber":7280,"code":0,"cities":["נחף","גיתה","מגדל תפן","לבון","כסרא סמיע","לפידות"],"timestampSec":1776074676,"timestampMs":1776074676000,"timestampIso":"2026-04-13T10:04:36.000Z"},{"serialNumber":7280,"code":0,"cities":["מג'דל כרום","כישור","בענה","תובל","דיר אל-אסד"],"timestampSec":1776074677,"timestampMs":1776074677000,"timestampIso":"2026-04-13T10:04:37.000Z"},{"serialNumber":7281,"code":5,"cities":["ראש הנקרה"],"timestampSec":1776075737,"timestampMs":1776075737000,"timestampIso":"2026-04-13T10:22:17.000Z"},{"serialNumber":7282,"code":5,"cities":["חוף בצת","ראש הנקרה"],"timestampSec":1776077533,"timestampMs":1776077533000,"timestampIso":"2026-04-13T10:52:13.000Z"},{"serialNumber":7282,"code":5,"cities":["שלומי"],"timestampSec":1776077543,"timestampMs":1776077543000,"timestampIso":"2026-04-13T10:52:23.000Z"},{"serialNumber":7282,"code":5,"cities":["בצת"],"timestampSec":1776077545,"timestampMs":1776077545000,"timestampIso":"2026-04-13T10:52:25.000Z"},{"serialNumber":7282,"code":5,"cities":["איזור תעשייה מילואות צפון"],"timestampSec":1776077549,"timestampMs":1776077549000,"timestampIso":"2026-04-13T10:52:29.000Z"},{"serialNumber":7282,"code":5,"cities":["לימן"],"timestampSec":1776077564,"timestampMs":1776077564000,"timestampIso":"2026-04-13T10:52:44.000Z"},{"serialNumber":7282,"code":5,"cities":["חוף אכזיב"],"timestampSec":1776077579,"timestampMs":1776077579000,"timestampIso":"2026-04-13T10:52:59.000Z"},{"serialNumber":7282,"code":5,"cities":["גשר הזיו"],"timestampSec":1776077647,"timestampMs":1776077647000,"timestampIso":"2026-04-13T10:54:07.000Z"},{"serialNumber":7282,"code":5,"cities":["נהריה"],"timestampSec":1776077655,"timestampMs":1776077655000,"timestampIso":"2026-04-13T10:54:15.000Z"},{"serialNumber":7282,"code":5,"cities":["סער"],"timestampSec":1776077681,"timestampMs":1776077681000,"timestampIso":"2026-04-13T10:54:41.000Z"},{"serialNumber":7283,"code":0,"cities":["כפר גלעדי","קריית שמונה","תל חי"],"timestampSec":1776079311,"timestampMs":1776079311000,"timestampIso":"2026-04-13T11:21:51.000Z"},{"serialNumber":7283,"code":0,"cities":["מטולה"],"timestampSec":1776079317,"timestampMs":1776079317000,"timestampIso":"2026-04-13T11:21:57.000Z"},{"serialNumber":7283,"code":0,"cities":["ג'ש - גוש חלב"],"timestampSec":1776079385,"timestampMs":1776079385000,"timestampIso":"2026-04-13T11:23:05.000Z"},{"serialNumber":7283,"code":0,"cities":["ברעם"],"timestampSec":1776079398,"timestampMs":1776079398000,"timestampIso":"2026-04-13T11:23:18.000Z"},{"serialNumber":7283,"code":0,"cities":["דוב''ב"],"timestampSec":1776079402,"timestampMs":1776079402000,"timestampIso":"2026-04-13T11:23:22.000Z"},{"serialNumber":7284,"code":0,"cities":["קריית שמונה"],"timestampSec":1776081600,"timestampMs":1776081600000,"timestampIso":"2026-04-13T12:00:00.000Z"},{"serialNumber":7284,"code":0,"cities":["מנרה","מרגליות"],"timestampSec":1776081609,"timestampMs":1776081609000,"timestampIso":"2026-04-13T12:00:09.000Z"},{"serialNumber":7285,"code":5,"cities":["זרעית"],"timestampSec":1776082800,"timestampMs":1776082800000,"timestampIso":"2026-04-13T12:20:00.000Z"},{"serialNumber":7285,"code":5,"cities":["שומרה"],"timestampSec":1776082819,"timestampMs":1776082819000,"timestampIso":"2026-04-13T12:20:19.000Z"},{"serialNumber":7286,"code":0,"cities":["ערב אל עראמשה"],"timestampSec":1776083306,"timestampMs":1776083306000,"timestampIso":"2026-04-13T12:28:26.000Z"},{"serialNumber":7286,"code":0,"cities":["מלכיה"],"timestampSec":1776083348,"timestampMs":1776083348000,"timestampIso":"2026-04-13T12:29:08.000Z"},{"serialNumber":7287,"code":0,"cities":["בצת","חניתה","ראש הנקרה","שלומי"],"timestampSec":1776084798,"timestampMs":1776084798000,"timestampIso":"2026-04-13T12:53:18.000Z"},{"serialNumber":7287,"code":0,"cities":["איזור תעשייה מילואות צפון","חוף בצת","לימן","מצובה"],"timestampSec":1776084803,"timestampMs":1776084803000,"timestampIso":"2026-04-13T12:53:23.000Z"},{"serialNumber":7287,"code":0,"cities":["נהריה"],"timestampSec":1776084807,"timestampMs":1776084807000,"timestampIso":"2026-04-13T12:53:27.000Z"},{"serialNumber":7287,"code":0,"cities":["חוף אכזיב"],"timestampSec":1776084808,"timestampMs":1776084808000,"timestampIso":"2026-04-13T12:53:28.000Z"},{"serialNumber":7287,"code":0,"cities":["גשר הזיו"],"timestampSec":1776084814,"timestampMs":1776084814000,"timestampIso":"2026-04-13T12:53:34.000Z"},{"serialNumber":7287,"code":0,"cities":["סער"],"timestampSec":1776084826,"timestampMs":1776084826000,"timestampIso":"2026-04-13T12:53:46.000Z"},{"serialNumber":7287,"code":0,"cities":["בצת"],"timestampSec":1776084837,"timestampMs":1776084837000,"timestampIso":"2026-04-13T12:53:57.000Z"},{"serialNumber":7288,"code":5,"cities":["איזור תעשייה מילואות צפון","בצת","חוף בצת","לימן","ראש הנקרה","שלומי","חוף אכזיב"],"timestampSec":1776085377,"timestampMs":1776085377000,"timestampIso":"2026-04-13T13:02:57.000Z"},{"serialNumber":7288,"code":5,"cities":["גשר הזיו"],"timestampSec":1776085399,"timestampMs":1776085399000,"timestampIso":"2026-04-13T13:03:19.000Z"},{"serialNumber":7288,"code":5,"cities":["נהריה"],"timestampSec":1776085400,"timestampMs":1776085400000,"timestampIso":"2026-04-13T13:03:20.000Z"},{"serialNumber":7288,"code":5,"cities":["סער"],"timestampSec":1776085421,"timestampMs":1776085421000,"timestampIso":"2026-04-13T13:03:41.000Z"},{"serialNumber":7288,"code":0,"cities":["כפר בלום","עמיר","שדה נחמיה"],"timestampSec":1776085479,"timestampMs":1776085479000,"timestampIso":"2026-04-13T13:04:39.000Z"},{"serialNumber":7288,"code":0,"cities":["מנרה","מרגליות","קריית שמונה"],"timestampSec":1776085487,"timestampMs":1776085487000,"timestampIso":"2026-04-13T13:04:47.000Z"},{"serialNumber":7288,"code":0,"cities":["קריית שמונה"],"timestampSec":1776085556,"timestampMs":1776085556000,"timestampIso":"2026-04-13T13:05:56.000Z"},{"serialNumber":7289,"code":0,"cities":["שתולה"],"timestampSec":1776085851,"timestampMs":1776085851000,"timestampIso":"2026-04-13T13:10:51.000Z"},{"serialNumber":7290,"code":0,"cities":["אביבים"],"timestampSec":1776086773,"timestampMs":1776086773000,"timestampIso":"2026-04-13T13:26:13.000Z"},{"serialNumber":7291,"code":5,"cities":["מג'דל שמס"],"timestampSec":1776090063,"timestampMs":1776090063000,"timestampIso":"2026-04-13T14:21:03.000Z"},{"serialNumber":7291,"code":5,"cities":["נווה אטי''ב"],"timestampSec":1776090104,"timestampMs":1776090104000,"timestampIso":"2026-04-13T14:21:44.000Z"},{"serialNumber":7292,"code":0,"cities":["חוסנייה","מכמנים - כמאנה מערבית"],"timestampSec":1776091914,"timestampMs":1776091914000,"timestampIso":"2026-04-13T14:51:54.000Z"},{"serialNumber":7292,"code":0,"cities":["מעלה צביה"],"timestampSec":1776091917,"timestampMs":1776091917000,"timestampIso":"2026-04-13T14:51:57.000Z"},{"serialNumber":7292,"code":0,"cities":["סכנין"],"timestampSec":1776091920,"timestampMs":1776091920000,"timestampIso":"2026-04-13T14:52:00.000Z"},{"serialNumber":7292,"code":0,"cities":["נחף","סאג'ור","אזור תעשייה כרמיאל","כרמיאל"],"timestampSec":1776091926,"timestampMs":1776091926000,"timestampIso":"2026-04-13T14:52:06.000Z"},{"serialNumber":7292,"code":0,"cities":["חוסן","כפר ורדים","מעלות תרשיחא","כסרא סמיע","מגדל תפן","פקיעין החדשה","פקיעין","צוריאל"],"timestampSec":1776091929,"timestampMs":1776091929000,"timestampIso":"2026-04-13T14:52:09.000Z"},{"serialNumber":7292,"code":0,"cities":["חרשים"],"timestampSec":1776091938,"timestampMs":1776091938000,"timestampIso":"2026-04-13T14:52:18.000Z"},{"serialNumber":7292,"code":0,"cities":["הר חלוץ","לבון"],"timestampSec":1776091943,"timestampMs":1776091943000,"timestampIso":"2026-04-13T14:52:23.000Z"},{"serialNumber":7293,"code":0,"cities":["קריית שמונה"],"timestampSec":1776093757,"timestampMs":1776093757000,"timestampIso":"2026-04-13T15:22:37.000Z"},{"serialNumber":7293,"code":0,"cities":["בית הלל"],"timestampSec":1776093758,"timestampMs":1776093758000,"timestampIso":"2026-04-13T15:22:38.000Z"},{"serialNumber":7294,"code":0,"cities":["גדות"],"timestampSec":1776094006,"timestampMs":1776094006000,"timestampIso":"2026-04-13T15:26:46.000Z"},{"serialNumber":7294,"code":0,"cities":["חולתה"],"timestampSec":1776094045,"timestampMs":1776094045000,"timestampIso":"2026-04-13T15:27:25.000Z"},{"serialNumber":7295,"code":0,"cities":["מרגליות"],"timestampSec":1776094360,"timestampMs":1776094360000,"timestampIso":"2026-04-13T15:32:40.000Z"},{"serialNumber":7295,"code":0,"cities":["קריית שמונה"],"timestampSec":1776094375,"timestampMs":1776094375000,"timestampIso":"2026-04-13T15:32:55.000Z"},{"serialNumber":7296,"code":5,"cities":["חניתה"],"timestampSec":1776098417,"timestampMs":1776098417000,"timestampIso":"2026-04-13T16:40:17.000Z"},{"serialNumber":7297,"code":0,"cities":["מלכיה"],"timestampSec":1776107072,"timestampMs":1776107072000,"timestampIso":"2026-04-13T19:04:32.000Z"},{"serialNumber":7298,"code":0,"cities":["יפתח","רמות נפתלי"],"timestampSec":1776109930,"timestampMs":1776109930000,"timestampIso":"2026-04-13T19:52:10.000Z"},{"serialNumber":7298,"code":5,"cities":["רמות נפתלי"],"timestampSec":1776109979,"timestampMs":1776109979000,"timestampIso":"2026-04-13T19:52:59.000Z"},{"serialNumber":7298,"code":5,"cities":["מלכיה"],"timestampSec":1776110147,"timestampMs":1776110147000,"timestampIso":"2026-04-13T19:55:47.000Z"}]}